toexcel/__init__.py
toexcel/pd2xl.py
toexcel/pyxl.py
toexcel/pyxlwt.py
toexcel/test.py
toexcel-1.0.3.dist-info/METADATA
toexcel-1.0.3.dist-info/WHEEL
toexcel-1.0.3.dist-info/top_level.txt
toexcel-1.0.3.dist-info/RECORD
