Metadata-Version: 2.1
Name: toexcel
Version: 1.0.3
Summary: 多场景数据转换至 Excel 表格工具。
Home-page: https://github.com/gary714/toexcel
Author: gary
Author-email: mepmb@sina.com
License: MIT
Project-URL: Homepage, https://github.com/gary714/toexcel
Project-URL: Documentation, https://github.com/gary714/toexcel
Project-URL: Source, https://github.com/gary714/toexcel
Keywords: Execl
Platform: Linux
Platform: Windows
Classifier: License :: OSI Approved :: MIT License
Classifier: Programming Language :: Python :: 3.6
Classifier: Programming Language :: Python :: 3.7
Classifier: Programming Language :: Python :: 3.8
Classifier: Programming Language :: Python :: 3.9
Requires-Dist: openpyxl==3.0.9
Requires-Dist: pandas==1.1.5
Requires-Dist: numpy==1.19.5
Requires-Dist: xlwt>=1.3.0
Requires-Dist: XlsxWriter>=3.0.1
